hosh/__init__.py
hosh/_internals_appearance.py
hosh/config.py
hosh/groups.py
hosh/hosh_.py
hosh/misc/__init__.py
hosh/misc/colors.py
hosh/misc/core.py
hosh/misc/encoding/__init__.py
hosh/misc/encoding/base.py
hosh/misc/encoding/base777.py
hosh/misc/exception.py
hosh/misc/helper.py
hosh/misc/identity.py
hosh/misc/math.py
hosh/misc/root.py
hosh/theme.py
hosh-3.250405.1.dist-info/LICENSE
hosh-3.250405.1.dist-info/METADATA
hosh-3.250405.1.dist-info/WHEEL
hosh-3.250405.1.dist-info/RECORD
