Metadata-Version: 2.3
Name: hosh
Version: 3.250405.1
Summary: Predictable Operable HaSH-based identifiers
License: GPL
Author: davips
Author-email: dpsabc@gmail.com
Requires-Python: >=3.8
Classifier: License :: Other/Proprietary License
Classifier: Programming Language :: Python :: 3
Classifier: Programming Language :: Python :: 3.8
Classifier: Programming Language :: Python :: 3.9
Classifier: Programming Language :: Python :: 3.10
Classifier: Programming Language :: Python :: 3.11
Classifier: Programming Language :: Python :: 3.12
Classifier: Programming Language :: Python :: 3.13
Requires-Dist: ansi2html (>=1.6.0,<2.0.0)
Requires-Dist: blake3 (>=1.0.4,<2.0.0)
Requires-Dist: bs4 (>=0.0.1,<0.0.2)
Requires-Dist: colored (==1.4.2)
Requires-Dist: twine (>=6.1.0,<7.0.0)
